spells/.ruff_cache/.gitignore
spells/.ruff_cache/0.8.6/17785301476771359756
spells/.ruff_cache/CACHEDIR.TAG
spells/__init__.py
spells/cache.py
spells/card_data_files.py
spells/cards.py
spells/columns.py
spells/config.py
spells/draft_data.py
spells/enums.py
spells/extension.py
spells/external.py
spells/filter.py
spells/log.py
spells/manifest.py
spells/schema.py
spells/utils.py
spells_mtg-0.11.20.dist-info/METADATA
spells_mtg-0.11.20.dist-info/WHEEL
spells_mtg-0.11.20.dist-info/entry_points.txt
spells_mtg-0.11.20.dist-info/licenses/LICENSE
spells_mtg-0.11.20.dist-info/RECORD
