Metadata-Version: 2.1
Name: spells-mtg
Version: 0.11.20
Summary: analaysis of 17Lands.com public datasets
Author-Email: Joel Barnes <oelarnes@gmail.com>
License: MIT
Requires-Python: >=3.11
Requires-Dist: polars==1.22.0
Requires-Dist: wget>=3.2
